LICENSE
README.md
setup.py
investimentos/__init__.py
investimentos/investimentos.py
meu_invest_andregon.egg-info/PKG-INFO
meu_invest_andregon.egg-info/SOURCES.txt
meu_invest_andregon.egg-info/dependency_links.txt
meu_invest_andregon.egg-info/top_level.txt
tests/test_investimentos.py