Metadata-Version: 2.4
Name: meu_invest_andregon
Version: 0.0.1
Summary: Uma biblioteca para cálculos de investimentos.
Author: Andre G Almeida
Author-email: tadriano.dev@gmail.com
Classifier: Programming Language :: Python :: 3
Classifier: License :: OSI Approved :: MIT License
Classifier: Operating System :: OS Independent
Requires-Python: >=3.6
License-File: LICENSE
Dynamic: author
Dynamic: author-email
Dynamic: classifier
Dynamic: license-file
Dynamic: requires-python
Dynamic: summary
